COPYING
CREDITS
MANIFEST.in
NEWS
README
jaxml.py
setup.py
jaxml.egg-info/PKG-INFO
jaxml.egg-info/SOURCES.txt
jaxml.egg-info/dependency_links.txt
jaxml.egg-info/top_level.txt
test/template.htt
test/test.py