Metadata-Version: 1.0
Name: jaxml
Version: 3.02
Summary: a Python module to generate XML easily
Home-page: http://www.librelogiciel.com/software/
Author: Jerome Alet
Author-email: alet@librelogiciel.com
License: GNU GPL
Platform: UNKNOWN
